{
  "kind": "collectionType",
  "collectionName": "parties",
  "info": {
    "singularName": "party",
    "pluralName": "parties",
    "displayName": "party",
    "description": ""
  },
  "options": {
    "draftAndPublish": true
  },
  "pluginOptions": {},
  "attributes": {
    "NAME": {
      "type": "string"
    },
    "TYPE": {
      "type": "enumeration",
      "enum": [
        "Individual",
        "Company"
      ]
    },
    "admin_user": {
      "type": "relation",
      "relation": "oneToOne",
      "target": "admin::user"
    },
    "GST_FROM_TS": {
      "type": "boolean"
    },
    "GST_TO_TS": {
      "type": "boolean"
    },
    "GST_NUMBER": {
      "type": "string"
    },
    "BILLING_ADDRESS": {
      "type": "text"
    },
    "BILLING_CITY": {
      "type": "string"
    },
    "BILLING_PINCODE": {
      "type": "string"
    },
    "BILLING_COUNTRY": {
      "type": "string"
    },
    "TS_TAKES_TDS": {
      "type": "boolean"
    },
    "TS_GIVES_TDS": {
      "type": "boolean"
    },
    "PAYMENT_TERMS": {
      "type": "integer"
    },
    "PRIMARY_EMAIL": {
      "type": "email"
    },
    "BILLING_STATE": {
      "type": "string"
    },
    "FOLLOW_UP_EMAIL_FREQ": {
      "type": "integer"
    },
    "party_emails": {
      "type": "relation",
      "relation": "oneToMany",
      "target": "api::party-email.party-email"
    },
    "party_profiles": {
      "type": "relation",
      "relation": "oneToMany",
      "target": "api::party-profile.party-profile"
    },
    "companies": {
      "type": "relation",
      "relation": "manyToMany",
      "target": "api::party.party",
      "inversedBy": "indviduals"
    },
    "indviduals": {
      "type": "relation",
      "relation": "manyToMany",
      "target": "api::party.party",
      "inversedBy": "companies"
    },
    "invoices": {
      "type": "relation",
      "relation": "manyToMany",
      "target": "api::invoice.invoice",
      "mappedBy": "sales"
    },
    "expenses": {
      "type": "relation",
      "relation": "oneToMany",
      "target": "api::expense.expense",
      "mappedBy": "RECEIVING_PARTY"
    }
  }
}
